monasca_agent/__init__.py
monasca_agent/version.py
monasca_agent/collector/__init__.py
monasca_agent/collector/daemon.py
monasca_agent/collector/jmxfetch.py
monasca_agent/collector/checks/__init__.py
monasca_agent/collector/checks/check.py
monasca_agent/collector/checks/collector.py
monasca_agent/collector/checks/services_checks.py
monasca_agent/collector/checks/utils.py
monasca_agent/collector/checks/libs/__init__.py
monasca_agent/collector/checks/libs/jmxfetch-0.3.0-jar-with-dependencies.jar
monasca_agent/collector/checks/libs/jmxterm-1.0-DATADOG-uber.jar
monasca_agent/collector/checks_d/__init__.py
monasca_agent/collector/checks_d/a10_system_check.py
monasca_agent/collector/checks_d/apache.py
monasca_agent/collector/checks_d/cacti.py
monasca_agent/collector/checks_d/cadvisor_host.py
monasca_agent/collector/checks_d/ceph.py
monasca_agent/collector/checks_d/cert_check.py
monasca_agent/collector/checks_d/cert_file_check.py
monasca_agent/collector/checks_d/check_mk_local.py
monasca_agent/collector/checks_d/congestion.py
monasca_agent/collector/checks_d/couch.py
monasca_agent/collector/checks_d/couchbase.py
monasca_agent/collector/checks_d/cpu.py
monasca_agent/collector/checks_d/crash.py
monasca_agent/collector/checks_d/directory.py
monasca_agent/collector/checks_d/disk.py
monasca_agent/collector/checks_d/docker.py
monasca_agent/collector/checks_d/elastic.py
monasca_agent/collector/checks_d/file_size.py
monasca_agent/collector/checks_d/gunicorn.py
monasca_agent/collector/checks_d/haproxy.py
monasca_agent/collector/checks_d/hdfs.py
monasca_agent/collector/checks_d/host_alive.py
monasca_agent/collector/checks_d/http_check.py
monasca_agent/collector/checks_d/http_metrics.py
monasca_agent/collector/checks_d/ib_network.py
monasca_agent/collector/checks_d/iis.py
monasca_agent/collector/checks_d/jenkins.py
monasca_agent/collector/checks_d/json_plugin.py
monasca_agent/collector/checks_d/kafka_consumer.py
monasca_agent/collector/checks_d/kibana.py
monasca_agent-10.0.0.dist-info/AUTHORS
monasca_agent-10.0.0.dist-info/LICENSE
monasca_agent-10.0.0.dist-info/METADATA
monasca_agent-10.0.0.dist-info/WHEEL
monasca_agent-10.0.0.dist-info/entry_points.txt
monasca_agent-10.0.0.dist-info/pbr.json
monasca_agent-10.0.0.dist-info/top_level.txt
monasca_agent-10.0.0.dist-info/RECORD
