Metadata-Version: 2.1
Name: monasca-agent
Version: 10.0.0
Summary: Monitoring agent for gathering metrics and sending them to the Monasca API.
Home-page: https://opendev.org/openstack/monasca-agent
Maintainer: OpenStack
Maintainer-email: openstack-discuss@lists.openstack.org
License: Apache-2
Keywords: openstack,monitoring
Platform: UNKNOWN
Classifier: Development Status :: 5 - Production/Stable
Classifier: License :: OSI Approved :: Apache Software License
Classifier: Topic :: System :: Monitoring
Classifier: Operating System :: POSIX :: Linux
Classifier: Programming Language :: Python :: 3
Classifier: Programming Language :: Python :: 3.6
Classifier: Programming Language :: Python :: 3.7
Classifier: Programming Language :: Python :: 3.8
Classifier: Programming Language :: Python :: 3.9
Classifier: Programming Language :: Python :: 3 :: Only
Classifier: Programming Language :: Python :: Implementation :: CPython
Requires-Python: >=3.6
Requires-Dist: PyYAML (>=3.10)
Requires-Dist: eventlet (!=0.18.3,!=0.20.1,>=0.18.2)
Requires-Dist: httplib2 (>=0.9.1)
Requires-Dist: keystoneauth1 (>=3.3.0)
Requires-Dist: monasca-common (>=2.7.0)
Requires-Dist: netaddr (>=0.7.18)
Requires-Dist: ntplib (<0.4,>=0.3.2)
Requires-Dist: oslo.concurrency (>=3.25.0)
Requires-Dist: oslo.config (>=5.2.0)
Requires-Dist: oslo.i18n (>=3.15.3)
Requires-Dist: oslo.utils (>=3.33.0)
Requires-Dist: oslo.vmware (>=2.17.0)
Requires-Dist: psutil (>=3.2.2)
Requires-Dist: pymongo (!=3.1,>=3.0.2)
Requires-Dist: python-keystoneclient (>=3.8.0)
Requires-Dist: python-memcached (>=1.56)
Requires-Dist: python-monascaclient (>=1.7.0)
Requires-Dist: redis (>=2.10.0)
Requires-Dist: requests (>=2.14.2)
Requires-Dist: stevedore (>=1.20.0)
Requires-Dist: tornado (>=4.5.3)
Provides-Extra: cert_file_check
Requires-Dist: cryptography (>=2.1) ; extra == 'cert_file_check'
Provides-Extra: influxdb
Requires-Dist: toml ; extra == 'influxdb'
Provides-Extra: influxdb_relay
Requires-Dist: toml ; extra == 'influxdb_relay'
Provides-Extra: kafka_plugin
Requires-Dist: monasca-common (>=1.4.0) ; extra == 'kafka_plugin'
Provides-Extra: libvirt
Requires-Dist: libvirt-python (>=3.5.0) ; extra == 'libvirt'
Requires-Dist: python-neutronclient (>=6.3.0) ; extra == 'libvirt'
Requires-Dist: python-novaclient (>=9.1.0) ; extra == 'libvirt'
Provides-Extra: ovs
Requires-Dist: python-neutronclient (>=6.3.0) ; extra == 'ovs'
Requires-Dist: python-novaclient (>=9.1.0) ; extra == 'ovs'
Provides-Extra: prometheus
Requires-Dist: prometheus-client ; extra == 'prometheus'
Provides-Extra: swift_handoffs
Requires-Dist: swift (>=2.0.0) ; extra == 'swift_handoffs'
Provides-Extra: test
Requires-Dist: bandit (!=1.6.0,>=1.1.0) ; extra == 'test'
Requires-Dist: coverage (!=4.4,>=4.0) ; extra == 'test'
Requires-Dist: docutils (>=0.11) ; extra == 'test'
Requires-Dist: freezegun (>=0.3.6) ; extra == 'test'
Requires-Dist: hacking (<3.1.0,>=3.0.1) ; extra == 'test'
Requires-Dist: oslotest (>=3.2.0) ; extra == 'test'
Requires-Dist: prometheus-client ; extra == 'test'
Requires-Dist: stestr (>=1.0.0) ; extra == 'test'
